{
  "ultima_hora": [
    {
      "hex": "348351",
      "chamada": "IBE0348",
      "cia": "Iberia",
      "pais": "Espanha",
      "bandeira": "🇪🇸",
      "local": "LEIRIA",
      "origem": "Boston, US",
      "destino": "Madrid, Espanha",
      "alt": "36000",
      "vel": "458.5",
      "dist": 19.6,
      "hora": "2025-10-10T03:55"
    },
    {
      "hex": "346045",
      "chamada": "IBE0124",
      "cia": "Iberia",
      "pais": "Espanha",
      "bandeira": "🇪🇸",
      "local": "RIO MAIOR",
      "origem": null,
      "destino": null,
      "alt": "37000",
      "vel": "464.5",
      "dist": 44.3,
      "hora": "2025-10-10T03:54"
    },
    {
      "hex": "aa9bb8",
      "chamada": "AAL68",
      "cia": "American Airlines",
      "pais": "Estados Unidos",
      "bandeira": "🇺🇸",
      "local": "FIGUEIRA DA FOZ",
      "origem": "Miami, US",
      "destino": "Madrid, Espanha",
      "alt": "39000",
      "vel": "497.7",
      "dist": 51.6,
      "hora": "2025-10-10T03:45"
    },
    {
      "hex": "394a18",
      "chamada": "AFR453",
      "cia": "Air France",
      "pais": "França",
      "bandeira": "🇫🇷",
      "local": "MONTIJO",
      "origem": "São Paulo, Brasil",
      "destino": "Paris, França",
      "alt": "36000",
      "vel": "456.5",
      "dist": 114.4,
      "hora": "2025-10-10T03:42"
    },
    {
      "hex": "4bb182",
      "chamada": "THY183",
      "cia": "Turkish Airlines",
      "pais": "Turquia",
      "bandeira": "🇹🇷",
      "local": "CARTAXO",
      "origem": "Istanbul, TR",
      "destino": "Istanbul, TR",
      "alt": "39000",
      "vel": "485.2",
      "dist": 67.5,
      "hora": "2025-10-10T03:39"
    },
    {
      "hex": "345251",
      "chamada": "AEA026",
      "cia": "Air Europa",
      "pais": "Espanha",
      "bandeira": "🇪🇸",
      "local": "MURTOSA",
      "origem": null,
      "destino": null,
      "alt": "40975",
      "vel": "464.9",
      "dist": 121.0,
      "hora": "2025-10-10T03:31"
    },
    {
      "hex": "34764a",
      "chamada": "IBE0156",
      "cia": "Iberia",
      "pais": "Espanha",
      "bandeira": "🇪🇸",
      "local": "NAZARÉ",
      "origem": null,
      "destino": null,
      "alt": "38000",
      "vel": "498.6",
      "dist": 13.3,
      "hora": "2025-10-10T03:26"
    },
    {
      "hex": "ae6877",
      "chamada": "",
      "cia": "",
      "pais": "Estados Unidos",
      "bandeira": "🇺🇸",
      "local": null,
      "origem": null,
      "destino": null,
      "alt": "30975",
      "vel": "",
      "dist": "",
      "hora": "2025-10-10T03:24"
    },
    {
      "hex": "0d09e5",
      "chamada": "AMX036",
      "cia": "Aeromexico",
      "pais": "México",
      "bandeira": "🇲🇽",
      "local": "ESPINHO",
      "origem": null,
      "destino": null,
      "alt": "39975",
      "vel": "492.8",
      "dist": 143.8,
      "hora": "2025-10-10T03:22"
    },
    {
      "hex": "3450d8",
      "chamada": "AEA138",
      "cia": "Air Europa",
      "pais": "Espanha",
      "bandeira": "🇪🇸",
      "local": null,
      "origem": "Quito, EC",
      "destino": "Madrid, Espanha",
      "alt": "40975",
      "vel": "",
      "dist": "",
      "hora": "2025-10-10T03:20"
    },
    {
      "hex": "ad727c",
      "chamada": "AMX027",
      "cia": "Aeromexico",
      "pais": "Estados Unidos",
      "bandeira": "🇺🇸",
      "local": "FIGUEIRA DA FOZ",
      "origem": null,
      "destino": null,
      "alt": "38975",
      "vel": "511.3",
      "dist": 52.1,
      "hora": "2025-10-10T03:04"
    },
    {
      "hex": "346310",
      "chamada": "AEA176",
      "cia": "Air Europa",
      "pais": "Espanha",
      "bandeira": "🇪🇸",
      "local": "MURTOSA",
      "origem": "Lima, Peru",
      "destino": "Madrid, Espanha",
      "alt": "38000",
      "vel": "483.3",
      "dist": 107.2,
      "hora": "2025-10-10T03:03"
    }
  ],
  "top_paises": [
    {
      "pais": "Espanha",
      "bandeira": "🇪🇸",
      "total": 6
    },
    {
      "pais": "Estados Unidos",
      "bandeira": "🇺🇸",
      "total": 3
    },
    {
      "pais": "México",
      "bandeira": "🇲🇽",
      "total": 1
    },
    {
      "pais": "Turquia",
      "bandeira": "🇹🇷",
      "total": 1
    },
    {
      "pais": "França",
      "bandeira": "🇫🇷",
      "total": 1
    }
  ],
  "top_companhias": [
    {
      "cia": "Air Europa",
      "total": 3
    },
    {
      "cia": "Iberia",
      "total": 3
    },
    {
      "cia": "Aeromexico",
      "total": 2
    },
    {
      "cia": "Turkish Airlines",
      "total": 1
    },
    {
      "cia": "Air France",
      "total": 1
    },
    {
      "cia": "American Airlines",
      "total": 1
    }
  ],
  "rotas": [
    {
      "hex": "346310",
      "chamada": "AEA176",
      "de": [
        40.707791,
        -8.828763
      ],
      "para": [
        40.638055,
        -8.349547
      ],
      "alt": "38000"
    },
    {
      "hex": "ad727c",
      "chamada": "AMX027",
      "de": [
        40.211683,
        -8.851859
      ],
      "para": [
        39.936447,
        -7.169373
      ],
      "alt": "38975"
    },
    {
      "hex": "0d09e5",
      "chamada": "AMX036",
      "de": [
        41.037706,
        -8.826079
      ],
      "para": [
        40.984637,
        -8.513031
      ],
      "alt": "39975"
    },
    {
      "hex": "34764a",
      "chamada": "IBE0156",
      "de": [
        39.629974,
        -8.96759
      ],
      "para": [
        39.714066,
        -7.81731
      ],
      "alt": "38000"
    },
    {
      "hex": "345251",
      "chamada": "AEA026",
      "de": [
        40.83418,
        -8.864032
      ],
      "para": [
        40.863461,
        -8.75317
      ],
      "alt": "40975"
    },
    {
      "hex": "4bb182",
      "chamada": "THY183",
      "de": [
        39.153411,
        -8.776306
      ],
      "para": [
        39.554764,
        -7.44879
      ],
      "alt": "39000"
    },
    {
      "hex": "394a18",
      "chamada": "AFR453",
      "de": [
        38.732025,
        -8.723204
      ],
      "para": [
        40.235053,
        -7.127318
      ],
      "alt": "36000"
    },
    {
      "hex": "aa9bb8",
      "chamada": "AAL68",
      "de": [
        40.226208,
        -8.971148
      ],
      "para": [
        39.935303,
        -7.169703
      ],
      "alt": "39000"
    },
    {
      "hex": "346045",
      "chamada": "IBE0124",
      "de": [
        39.350281,
        -8.902568
      ],
      "para": [
        39.499146,
        -8.112985
      ],
      "alt": "37000"
    },
    {
      "hex": "348351",
      "chamada": "IBE0348",
      "de": [
        39.917084,
        -8.874625
      ],
      "para": [
        39.891632,
        -8.218251
      ],
      "alt": "36000"
    }
  ]
}